errorcode_sdk/__init__.py
errorcode_sdk/error_codes.py
errorcode_sdk-0.1.0.dist-info/METADATA
errorcode_sdk-0.1.0.dist-info/WHEEL
errorcode_sdk-0.1.0.dist-info/top_level.txt
errorcode_sdk-0.1.0.dist-info/RECORD
